api_dock/__init__.py
api_dock/cli.py
api_dock/config.py
api_dock/config_discovery.py
api_dock/database_config.py
api_dock/fast_api.py
api_dock/flask_api.py
api_dock/route_mapper.py
api_dock/sql_builder.py
api_dock-0.0.5.dist-info/licenses/LICENSE.md
config/config.yaml
config/databases/db_example.yaml
config/remotes/remote_with_allowed_routes.yaml
config/remotes/remote_with_custom_mapping.yaml
config/remotes/remote_with_restrictions.yaml
api_dock-0.0.5.dist-info/METADATA
api_dock-0.0.5.dist-info/WHEEL
api_dock-0.0.5.dist-info/entry_points.txt
api_dock-0.0.5.dist-info/top_level.txt
api_dock-0.0.5.dist-info/RECORD
