Metadata-Version: 2.4
Name: api_dock
Version: 0.0.5
Summary: A flexible API gateway that allows you to proxy requests to multiple remote APIs and Databases
Author-email: Brookie Guzder-Williams <bguzder-williams@berkeley.edu>
License: BSd 3-clause
Classifier: Development Status :: 4 - Beta
Classifier: Intended Audience :: Developers
Classifier: Programming Language :: Python :: 3
Classifier: Programming Language :: Python :: 3.8
Classifier: Programming Language :: Python :: 3.9
Classifier: Programming Language :: Python :: 3.10
Classifier: Programming Language :: Python :: 3.11
Classifier: Programming Language :: Python :: 3.12
Classifier: Topic :: Database
Classifier: Topic :: Internet :: WWW/HTTP
Classifier: Topic :: Software Development :: Libraries
Classifier: Topic :: Scientific/Engineering
Requires-Python: >=3.11
License-File: LICENSE.md
Requires-Dist: click
Requires-Dist: fastapi
Requires-Dist: uvicorn
Requires-Dist: pyyaml
Requires-Dist: httpx
Requires-Dist: duckdb
Requires-Dist: flask
Dynamic: license-file
